{
  "name": "홍성휘",
  "phone": "010-5270-5964",
  "email": "tnfy10@gmail.com",
  "profileImageUrl": "https://firebasestorage.googleapis.com/v0/b/sunghwi-portfolio.firebasestorage.app/o/images%2Fprofile.jpg?alt=media&token=c5547bf2-559d-465e-8766-147a7b41015c",
  "intro": "4년차 안드로이드 개발자로 앱 개발부터 출시, 그리고 수익화를 위한 인앱 결제 구현 경험이 있습니다. 최근에는 핀테크 업계에서 3년 이상 근무하며 금융 기술을 다뤄왔으며, 신규 프로젝트에 참여하여 기획부터 개발 그리고 배포까지 전반적인 과정을 경험했습니다. 특히, 커스텀 UI 개발 및 성능 최적화, 그리고 기술적인 문제 해결에 능숙합니다. 새로운 기술을 배우고 적용하는 것을 즐기며, 동료들과 적극적으로 소통하고 협업하여 함께 성장하는 것을 중요하게 생각합니다. 사용자 중심의 개발을 지향하며, 끊임없는 학습을 통해 최고의 결과물을 만들기 위해 노력합니다."
}